[{
    "id": 860,
    "firstName": "Superman",
    "lastName": "Yoda"
}, {
    "id": 870,
    "firstName": "Foo",
    "lastName": "Whateveryournameis"
}, {
    "id": 590,
    "firstName": "Toto",
    "lastName": "Titi"
}, {
    "id": 804,
    "firstName": "Luke",
    "lastName": "Kyle"
}, {
    "id": 805,
    "firstName": "Luke",
    "lastName": "Kyle"
}, {
    "id": 806,
    "firstName": "Luke",
    "lastName": "Kyle"
}, {
    "id": 807,
    "firstName": "Luke",
    "lastName": "Kyle"
}, {
    "id": 808,
    "firstName": "Luke",
    "lastName": "Kyle"
}, {
    "id": 809,
    "firstName": "Luke",
    "lastName": "Kyle"
}, {
    "id": 800,
    "firstName": "Luke",
    "lastName": "Kyle"
}, {
    "id": 812,
    "firstName": "Luke",
    "lastName": "Kyle"
}, {
    "id": 823,
    "firstName": "Luke",
    "lastName": "Kyle"
}
]
